python_claml/__init__.py
python_claml/__version__.py
python_claml/claml.py
python_claml/claml_types.py
python_claml-0.1.1.dist-info/LICENSE
python_claml-0.1.1.dist-info/METADATA
python_claml-0.1.1.dist-info/WHEEL
python_claml-0.1.1.dist-info/top_level.txt
python_claml-0.1.1.dist-info/RECORD
