Metadata-Version: 2.1
Name: python-claml
Version: 0.1.1
Summary: A ClaML reader for Python.
Home-page: https://github.com/thehyve/python_claml
Author: Gijs Kant
Author-email: gijs@thehyve.nl
License: MIT
Keywords: python_claml
Platform: UNKNOWN
Classifier: Development Status :: 2 - Pre-Alpha
Classifier: Intended Audience :: Developers
Classifier: License :: OSI Approved :: MIT License
Classifier: Natural Language :: English
Classifier: Programming Language :: Python :: 3
Classifier: Programming Language :: Python :: 3.6
Requires-Python: >=3.6.0
Requires-Dist: pyxb (<1.3.0,>=1.2.6)
